{"GlobalPropertiesHash":"xhiKb/Ecs8p9EqR/cfRIWix38XTzp1TX2wfbTyw2xfA=","FingerprintPatternsHash":"gq3WsqcKBUGTSNle7RKKyXRIwh7M8ccEqOqYvIzoM04=","PropertyOverridesHash":"8ZRc1sGeVrPBx4lD717BgRaQekyh78QKV9SKsdt638U=","InputHashes":["Wn1NTo/HP/\u002BQcnOxQke\u002B840xEEa2SiG3E3dTYJJlEAA=","5hc584hQ6Ty66XR5mBPSHPv7ZvYxbg4oFJsKQuMaVKg=","DAjoMytmQlJPL\u002BBgsOOuo433oBQK5AGu/T73GGYdF8E=","1rFdtVY1s/D169yHEoUhmCzvdvM6LEy9QettLw\u002BQNLw=","IKDuIaOkx7RqHl5MZYHTKOFFv8FzoIx4/OTgM5CyVZI=","rNYJAgf6PWsYswT6/WbvtsSkM\u002BPwe/FJu8tMcsNzPhk=","QWR9F6mo69RuRIR\u002BvKpxsDdzlHD1WUaCE\u002BnRGjn622E=","98tLU8unijGWKTvfP/pP/bmOePyjZFvmEbGtYnpVhMo=","NSTnyOYu8ipzR7adKQvr67v6BWEc2C/eAFYT6wF\u002BbHE=","hJJn2813IpHiKLZb1B/yxIa0pFqBl70Jud0LECWohWQ=","ieSAuo/taPSEeEBGcHvECuqSay8yTpuP5FA60IIkohk=","axiaFyk65epr0bp1f4wE4Q4vYQwCv0okuSW6tBs0EBs=","LDHAqhgAyY3W/p\u002BZxG5Kho54l0\u002BKGhBo9004fwCHJd8=","I4ff3woMhnJFdEGV2Ew\u002BSKIQgCOBiYCR5PCoy1mR0Fk=","q3U55FR14wnG1Tk\u002BYzVLNMfxAUu8/EMcDy7DdMHFmmQ=","mXEcUE8seDUuUWp\u002BtsOYVqYNVm4FD8x2nFQoV5B2Nb4=","w2DVWdCk2tWThhxPg36K32AIKAbcDHMiz42oSk6DGbM="],"CachedAssets":{"5hc584hQ6Ty66XR5mBPSHPv7ZvYxbg4oFJsKQuMaVKg=":{"Identity":"c:\\Users\\beatr\\Videos\\Plataforma_Interativa_Infantil\\Plataforma_Interativa_Infantil\\wwwroot\\js\\site.js","SourceId":"PlataformaEducacao","SourceType":"Discovered","ContentRoot":"c:\\Users\\beatr\\Videos\\Plataforma_Interativa_Infantil\\Plataforma_Interativa_Infantil\\wwwroot\\","BasePath":"_content/PlataformaEducacao","RelativePath":"js/site#[.{fingerprint}]?.js","AssetKind":"All","AssetMode":"All","AssetRole":"Primary","AssetMergeBehavior":null,"AssetMergeSource":"","RelatedAsset":null,"AssetTraitName":null,"AssetTraitValue":null,"Fingerprint":"cjnn9xmo71","Integrity":"GPys50vYQLaKpRnJ9QWNRhDnbFivXsv5dGwMzybXkbY=","CopyToOutputDirectory":"Never","CopyToPublishDirectory":"PreserveNewest","OriginalItemSpec":"wwwroot\\js\\site.js","FileLength":5558,"LastWriteTime":"2025-10-09T20:00:39.2970166+00:00"},"Wn1NTo/HP/\u002BQcnOxQke\u002B840xEEa2SiG3E3dTYJJlEAA=":{"Identity":"c:\\Users\\beatr\\Videos\\Plataforma_Interativa_Infantil\\Plataforma_Interativa_Infantil\\wwwroot\\css\\site.css","SourceId":"PlataformaEducacao","SourceType":"Discovered","ContentRoot":"c:\\Users\\beatr\\Videos\\Plataforma_Interativa_Infantil\\Plataforma_Interativa_Infantil\\wwwroot\\","BasePath":"_content/PlataformaEducacao","RelativePath":"css/site#[.{fingerprint}]?.css","AssetKind":"All","AssetMode":"All","AssetRole":"Primary","AssetMergeBehavior":null,"AssetMergeSource":"","RelatedAsset":null,"AssetTraitName":null,"AssetTraitValue":null,"Fingerprint":"huubtrfxnr","Integrity":"F9b1HGK86hjx4bahfG5i7sB1TRebvLQCgWLkZKpmXzg=","CopyToOutputDirectory":"Never","CopyToPublishDirectory":"PreserveNewest","OriginalItemSpec":"wwwroot\\css\\site.css","FileLength":2921,"LastWriteTime":"2025-10-09T20:00:39.2970166+00:00"}},"CachedCopyCandidates":{}}